u2t/__init__.py
u2t/resources/icon/normal.ico
u2t/resources/icon/running.ico
u2t-1.0.3.dist-info/LICENSE
u2t-1.0.3.dist-info/METADATA
u2t-1.0.3.dist-info/WHEEL
u2t-1.0.3.dist-info/entry_points.txt
u2t-1.0.3.dist-info/top_level.txt
u2t-1.0.3.dist-info/RECORD
