Metadata-Version: 2.1
Name: u2t
Version: 1.0.3
Summary: A tool helps to convert url to markdown style url format
Home-page: https://github.com/WangYihang/Markdown-URL-to-Title
Author: Wang Yihang
Author-email: wangyihanger@gmail.com
License: UNKNOWN
Keywords: markdown,url,editor
Platform: UNKNOWN
Classifier: Programming Language :: Python :: 3
Classifier: Operating System :: Microsoft :: Windows
Classifier: Development Status :: 5 - Production/Stable
Classifier: Topic :: Text Processing :: Markup :: Markdown
Classifier: License :: OSI Approved :: GNU Lesser General Public License v3 (LGPLv3)
Requires-Python: >=3.6
Requires-Dist: bs4
Requires-Dist: clipboard
Requires-Dist: infi.systray
Requires-Dist: requests
Requires-Dist: system-hotkey
Requires-Dist: win10toast
